geode_implicit/__init__.py
geode_implicit/__init__.pyi
geode_implicit/explicitation.py
geode_implicit/explicitation.pyi
geode_implicit/implicitation.py
geode_implicit/implicitation.pyi
geode_implicit/insertion.py
geode_implicit/insertion.pyi
geode_implicit/model_io.py
geode_implicit/model_io.pyi
geode_implicit/py.typed
geode_implicit/workflows.py
geode_implicit/workflows.pyi
geode_implicit/lib64/__init__.pyi
geode_implicit/lib64/geode_implicit_py_explicitation.cpython-311-x86_64-linux-gnu.so
geode_implicit/lib64/geode_implicit_py_explicitation.pyi
geode_implicit/lib64/geode_implicit_py_implicitation.cpython-311-x86_64-linux-gnu.so
geode_implicit/lib64/geode_implicit_py_implicitation.pyi
geode_implicit/lib64/geode_implicit_py_insertion.cpython-311-x86_64-linux-gnu.so
geode_implicit/lib64/geode_implicit_py_insertion.pyi
geode_implicit/lib64/geode_implicit_py_io.cpython-311-x86_64-linux-gnu.so
geode_implicit/lib64/geode_implicit_py_io.pyi
geode_implicit/lib64/geode_implicit_py_workflows.cpython-311-x86_64-linux-gnu.so
geode_implicit/lib64/geode_implicit_py_workflows.pyi
geode_implicit/lib64/libGeode-Implicit_explicitation.so
geode_implicit/lib64/libGeode-Implicit_implicitation.so
geode_implicit/lib64/libGeode-Implicit_insertion.so
geode_implicit/lib64/libGeode-Implicit_io.so
geode_implicit/lib64/libGeode-Implicit_workflows.so
geode_implicit-4.4.2.dist-info/METADATA
geode_implicit-4.4.2.dist-info/WHEEL
geode_implicit-4.4.2.dist-info/top_level.txt
geode_implicit-4.4.2.dist-info/RECORD
