Metadata-Version: 2.4
Name: Geode-Implicit
Version: 4.4.2
Summary: Licensed framework for working with implicit modeling
Author-email: Geode-solutions <contact@geode-solutions.com>
License: Proprietary
Requires-Python: <3.13,>=3.9
Requires-Dist: geode-background==9.*,>=9.8.6
Requires-Dist: geode-common==33.*,>=33.14.4
Requires-Dist: geode-conversion==6.*,>=6.5.9
Requires-Dist: geode-explicit==6.*,>=6.6.7
Requires-Dist: geode-numerics==6.*,>=6.4.9
Requires-Dist: geode-simplex==9.*,>=9.8.15
Requires-Dist: opengeode-core==15.*,>=15.30.10
Requires-Dist: opengeode-geosciences==9.*,>=9.5.6
Requires-Dist: opengeode-geosciencesio==5.*,>=5.8.7
Requires-Dist: opengeode-inspector==6.*,>=6.8.12
Requires-Dist: opengeode-io==7.*,>=7.4.6
